dear_messenger/__init__.py
dear_messenger/__main__.py
dear_messenger-1.0.0.dist-info/entry_points.txt
dear_messenger-1.0.0.dist-info/METADATA
dear_messenger-1.0.0.dist-info/WHEEL
dear_messenger-1.0.0.dist-info/RECORD
